statsig/__init__.py
statsig/batch_event_queue.py
statsig/client_initialize_formatter.py
statsig/config_evaluation.py
statsig/constants.py
statsig/diagnostics.py
statsig/dynamic_config.py
statsig/evaluation_context.py
statsig/evaluation_details.py
statsig/evaluator.py
statsig/feature_gate.py
statsig/globals.py
statsig/grpc_websocket_worker.py
statsig/grpc_worker.py
statsig/http_worker.py
statsig/initialize_details.py
statsig/interface_data_store.py
statsig/interface_network.py
statsig/interface_observability_client.py
statsig/layer.py
statsig/output_logger.py
statsig/py.typed
statsig/redis_data_store.py
statsig/request_result.py
statsig/sdk_configs.py
statsig/spec_store.py
statsig/spec_updater.py
statsig/statsig.py
statsig/statsig_context.py
statsig/statsig_environment_tier.py
statsig/statsig_error_boundary.py
statsig/statsig_errors.py
statsig/statsig_event.py
statsig/statsig_logger.py
statsig/statsig_logger_worker.py
statsig/statsig_metadata.py
statsig/statsig_network.py
statsig/statsig_options.py
statsig/statsig_server.py
statsig/statsig_telemetry_logger.py
statsig/statsig_user.py
statsig/stream_decompressor.py
statsig/thread_util.py
statsig/ttl_set.py
statsig/utils.py
statsig/version.py
statsig/grpc/__init__.py
statsig/grpc/generated/__init__.py
statsig/grpc/generated/statsig_forward_proxy_pb2.py
statsig/grpc/generated/statsig_forward_proxy_pb2.pyi
statsig/grpc/generated/statsig_forward_proxy_pb2_grpc.py
statsig-0.67.0.dist-info/licenses/LICENSE
statsig-0.67.0.dist-info/METADATA
statsig-0.67.0.dist-info/WHEEL
statsig-0.67.0.dist-info/top_level.txt
statsig-0.67.0.dist-info/RECORD
