Metadata-Version: 2.4
Name: statsig
Version: 0.67.0
Summary: Statsig Python Server SDK
Home-page: https://github.com/statsig-io/python-sdk
Author: Tore Hanssen, Jiakan Wang
Author-email: tore@statsig.com, jkw@statsig.com
License: ISC
Classifier: Intended Audience :: Developers
Classifier: Programming Language :: Python
Classifier: Programming Language :: Python :: 3
Classifier: Topic :: Software Development :: Libraries
Requires-Python: >=3.7
License-File: LICENSE
Requires-Dist: requests
Requires-Dist: ua_parser
Requires-Dist: ip3country
Requires-Dist: grpcio
Requires-Dist: protobuf
Requires-Dist: ijson
Requires-Dist: typing-extensions
Requires-Dist: brotli
Provides-Extra: test
Requires-Dist: requests; extra == "test"
Requires-Dist: user_agents; extra == "test"
Requires-Dist: semver; extra == "test"
Dynamic: author
Dynamic: author-email
Dynamic: classifier
Dynamic: description
Dynamic: description-content-type
Dynamic: home-page
Dynamic: license
Dynamic: license-file
Dynamic: provides-extra
Dynamic: requires-dist
Dynamic: requires-python
Dynamic: summary
